customlib/__init__.py
customlib/utils.py
customlib/filehandlers/__init__.py
customlib/filehandlers/constants.py
customlib/filehandlers/handlers.py
customlib/filehandlers/utils.py
customlib/filelockers/__init__.py
customlib/filelockers/constants.py
customlib/filelockers/core.py
customlib/filelockers/exceptions.py
customlib/filelockers/handlers.py
customlib/keyvault/__init__.py
customlib/keyvault/exceptions.py
customlib/keyvault/handlers.py
customlib/keyvault/utils.py
customlib/registry/__init__.py
customlib/registry/exceptions.py
customlib/registry/handlers.py
customlib/singletons/__init__.py
customlib/singletons/constants.py
customlib/singletons/handlers.py
customlib/systemhandlers/__init__.py
customlib/systemhandlers/constants.py
customlib/systemhandlers/handlers.py
customlib-6.3.0.dist-info/LICENSE
customlib-6.3.0.dist-info/METADATA
customlib-6.3.0.dist-info/WHEEL
customlib-6.3.0.dist-info/top_level.txt
customlib-6.3.0.dist-info/RECORD
