Metadata-Version: 2.1
Name: customlib
Version: 6.3.0
Summary: Custom library.
Home-page: https://github.com/ClaudiuDrug/custom-library
Author: Claudiu DRUG
Author-email: claudiu.drug@outlook.com
License: MIT License
Project-URL: Bug Tracker, https://github.com/ClaudiuDrug/custom-library/issues
Classifier: Programming Language :: Python :: 3.7
Classifier: Programming Language :: Python :: 3.8
Classifier: Programming Language :: Python :: 3.9
Classifier: Programming Language :: Python :: 3.10
Classifier: License :: OSI Approved :: MIT License
Classifier: Operating System :: Microsoft :: Windows :: Windows 10
Classifier: Operating System :: POSIX :: Linux
Classifier: Intended Audience :: Developers
Classifier: Natural Language :: English
Classifier: Topic :: Software Development :: Libraries :: Python Modules
Classifier: Topic :: Utilities
Requires-Python: >=3.7
License-File: LICENSE
Requires-Dist: cryptography (==38.0.3)
Requires-Dist: keyring (==23.11.0)
Requires-Dist: pywin32 (==305) ; platform_system == "Windows"
